{
  "parent": "minecraft:recipes/root",
  "rewards": {
    "recipes": [
      "netherupdateplus:silver_tungsten_axe"
    ]
  },
  "criteria": {
    "hasItemsilver": {
      "trigger": "minecraft:inventory_changed",
      "conditions": {
        "items": [
          {
            "item": "netherupdateplus:silver_tungsten_ingot"
          }
        ]
      }
    },
    "has_the_recipe": {
      "trigger": "minecraft:recipe_unlocked",
      "conditions": {
        "recipe": "netherupdateplus:silver_tungsten_axe"
      }
    }
  },
  "requirements": [
    [
      "hasItemsilver",
      "has_the_recipe"
    ]
  ]
}